<?xml version = '1.0' encoding = 'UTF-8'?>
<Diagram class="oracle.dbtools.crest.swingui.relational.DPVRelational" name="Relational_1" id="02B429CD-DEDD-9FE0-8A4D-18D8B54E58F1">
<createdBy>laris</createdBy>
<modifiedBy>laris</modifiedBy>
<createdTime>2025-05-28 23:44:54 UTC</createdTime>
<autoRoute>false</autoRoute>
<boxInbox>true</boxInbox>
<showLegend>false</showLegend>
<showLabels>false</showLabels>
<showRelAttributes>false</showRelAttributes>
<gridEnabled>false</gridEnabled>
<showGrid>false</showGrid>
<diagramColor>-1</diagramColor>
<display>false</display>
<notation>1</notation>
<objectViews>
<OView class="oracle.dbtools.crest.swingui.relational.TVTable" oid="230630EB-21CD-7A12-E8AF-A65EFDCC8680" otype="Table" vid="B9073AD9-CF96-4EAC-D1F9-7A9A54B99A37">
<hideElementsInCurrentOnly>false</hideElementsInCurrentOnly>
<bounds x="1374" y="352" width="170" height="110"/>
</OView>
<OView class="oracle.dbtools.crest.swingui.relational.TVTable" oid="4C6BA838-9F52-9D9F-E9E4-24995D195E05" otype="Table" vid="79B80AC9-6832-7C22-7317-223D0136D577">
<hideElementsInCurrentOnly>false</hideElementsInCurrentOnly>
<bounds x="74" y="358" width="341" height="122"/>
</OView>
<OView class="oracle.dbtools.crest.swingui.relational.TVTable" oid="801E81A0-79AC-EFB3-B77C-D283918898D6" otype="Table" vid="E15F9E8B-785C-A9A7-8CBF-8E06CB05A709">
<hideElementsInCurrentOnly>false</hideElementsInCurrentOnly>
<bounds x="589" y="193" width="170" height="110"/>
</OView>
<OView class="oracle.dbtools.crest.swingui.relational.TVTable" oid="AE653E1D-6A8D-73D0-EF3A-EF41CB173B57" otype="Table" vid="8B41AFEE-BCAF-51EC-C0D1-838D0028E8BC">
<hideElementsInCurrentOnly>false</hideElementsInCurrentOnly>
<bounds x="1080" y="170" width="170" height="110"/>
</OView>
<OView class="oracle.dbtools.crest.swingui.relational.TVTable" oid="C59102F7-4466-D0B2-7635-A59C1132584B" otype="Table" vid="75828BC0-8C87-5F33-1619-4F73A0FA5959">
<hideElementsInCurrentOnly>false</hideElementsInCurrentOnly>
<bounds x="84" y="65" width="389" height="173"/>
</OView>
<OView class="oracle.dbtools.crest.swingui.relational.TVTable" oid="E7337BE7-447A-2E41-A724-A9A502D1B4A7" otype="Table" vid="CD6C3F71-29B5-1C10-577C-D90A5A0FA276">
<hideElementsInCurrentOnly>false</hideElementsInCurrentOnly>
<bounds x="852" y="40" width="170" height="110"/>
</OView>
</objectViews>
<connectors>
<Connector class="oracle.dbtools.crest.swingui.relational.TVFKRelation" oid="18DAB768-14AF-0039-8FE0-EDEB514A1439" otype="FKIndexAssociation" vid_source="CD6C3F71-29B5-1C10-577C-D90A5A0FA276" vid_target="8B41AFEE-BCAF-51EC-C0D1-838D0028E8BC">
<hideElementsInCurrentOnly>false</hideElementsInCurrentOnly>
<backgroundColor>-16777216</backgroundColor>
<lineWidth>1</lineWidth>
<points>
<point x="1022" y="143"/>
<point x="1080" y="176"/>
</points>
</Connector>
<Connector class="oracle.dbtools.crest.swingui.relational.TVFKRelation" oid="28072353-4C7D-D21F-5BEC-752D15CCE62D" otype="FKIndexAssociation" vid_source="B9073AD9-CF96-4EAC-D1F9-7A9A54B99A37" vid_target="8B41AFEE-BCAF-51EC-C0D1-838D0028E8BC">
<hideElementsInCurrentOnly>false</hideElementsInCurrentOnly>
<backgroundColor>-16777216</backgroundColor>
<lineWidth>1</lineWidth>
<points>
<point x="1374" y="354"/>
<point x="1250" y="277"/>
</points>
</Connector>
<Connector class="oracle.dbtools.crest.swingui.relational.TVFKRelation" oid="7401537D-B7A8-F622-A260-697F94D5D21B" otype="FKIndexAssociation" vid_source="E15F9E8B-785C-A9A7-8CBF-8E06CB05A709" vid_target="75828BC0-8C87-5F33-1619-4F73A0FA5959">
<hideElementsInCurrentOnly>false</hideElementsInCurrentOnly>
<backgroundColor>-16777216</backgroundColor>
<lineWidth>1</lineWidth>
<points>
<point x="589" y="215"/>
<point x="473" y="215"/>
</points>
</Connector>
<Connector class="oracle.dbtools.crest.swingui.relational.TVFKRelation" oid="76974895-66AC-70BB-1D47-9E42AF76BEF2" otype="FKIndexAssociation" vid_source="79B80AC9-6832-7C22-7317-223D0136D577" vid_target="75828BC0-8C87-5F33-1619-4F73A0FA5959">
<hideElementsInCurrentOnly>false</hideElementsInCurrentOnly>
<backgroundColor>-16777216</backgroundColor>
<lineWidth>1</lineWidth>
<points>
<point x="249" y="358"/>
<point x="249" y="238"/>
</points>
</Connector>
<Connector class="oracle.dbtools.crest.swingui.relational.TVFKRelation" oid="D742A796-6CE9-3F42-8A6F-855E174068CC" otype="FKIndexAssociation" vid_source="E15F9E8B-785C-A9A7-8CBF-8E06CB05A709" vid_target="CD6C3F71-29B5-1C10-577C-D90A5A0FA276">
<hideElementsInCurrentOnly>false</hideElementsInCurrentOnly>
<backgroundColor>-16777216</backgroundColor>
<lineWidth>1</lineWidth>
<points>
<point x="759" y="198"/>
<point x="852" y="144"/>
</points>
</Connector>
</connectors>
</Diagram>